LICENSE_EN.txt
LICENSE_FR.txt
MANIFEST.in
README.rst
VERSION.txt
requirements.txt
setup.cfg
setup.py
conf/eureka.cfg
data/attachments/EMPTY_DIR
data/board/EMPTY_DIR
data/fixtures/article_topics.csv
data/fixtures/domains.csv
data/fixtures/improvement_domains.csv
data/fixtures/organizations.csv
data/improvements/EMPTY_DIR
data/locale/messages.pot
data/locale/en/LC_MESSAGES/messages.mo
data/locale/en/LC_MESSAGES/messages.po
data/locale/fr/LC_MESSAGES/messages.mo
data/locale/fr/LC_MESSAGES/messages.po
data/logs/eureka/EMPTY_DIR
data/logs/httpd/EMPTY_DIR
data/logs/mail/EMPTY_DIR
data/logs/solr/EMPTY_DIR
data/logs/supervisord/EMPTY_DIR
data/profile-photo/default.png
data/profile-thumbnails/100x100/default.png
data/profile-thumbnails/30x30/default.png
data/profile-thumbnails/40x40/default.png
data/profile-thumbnails/90x90/default.png
data/run/supervisord/EMPTY_DIR
data/staticcontent/en/faq.xml
data/staticcontent/en/online_shop.xml
data/staticcontent/en/terms_of_use.xml
data/staticcontent/en/welcome.xml
data/staticcontent/fr/faq.xml
data/staticcontent/fr/online_shop.xml
data/staticcontent/fr/terms_of_use.xml
data/staticcontent/fr/welcome.xml
data/templates/en/mail-developer-replaced.html
data/templates/en/mail-event-comment-added.html
data/templates/en/mail-event-state-changed.html
data/templates/en/mail-followed-user-notify.html
data/templates/en/mail-idea-deployed.html
data/templates/en/mail-idea-forward-for-di.html
data/templates/en/mail-idea-forward-for-dsig-di.html
data/templates/en/mail-idea-forward-for-dsig-fi.html
data/templates/en/mail-idea-needs-info-di.html
data/templates/en/mail-idea-needs-info.html
data/templates/en/mail-idea-published.html
data/templates/en/mail-idea-recommended.html
data/templates/en/mail-idea-refused-by-fi.html
data/templates/en/mail-idea-refused-by-ips.html
data/templates/en/mail-idea-refused.html
data/templates/en/mail-idea-selected.html
data/templates/en/mail-idea-submitted-for-authors.html
eureka_opensource.egg-info/PKG-INFO
eureka_opensource.egg-info/SOURCES.txt
eureka_opensource.egg-info/dependency_links.txt
eureka_opensource.egg-info/entry_points.txt
eureka_opensource.egg-info/not-zip-safe
eureka_opensource.egg-info/requires.txt
eureka_opensource.egg-info/top_level.txt
