Metadata-Version: 1.0
Name: eureka-opensource
Version: 1.0.3
Summary: Innovative think tank web application
Home-page: https://eureka-opensource.solocalgroup.com
Author: Solocal Group
Author-email: eureka@solocal.com
License: CeCILL
Keywords: innovation,web,application
Platform: UNKNOWN
